dsa_helpers/__init__.py
dsa_helpers/cli_utils.py
dsa_helpers/girder_utils.py
dsa_helpers/gpd_utils.py
dsa_helpers/image_utils.py
dsa_helpers/imread.py
dsa_helpers/imwrite.py
dsa_helpers/mongo_utils.py
dsa_helpers/tile_utils.py
dsa_helpers/tiling.py
dsa_helpers/utils.py
dsa_helpers/dash/__init__.py
dsa_helpers/dash/dash_paperdragon_utils.py
dsa_helpers/dash/header.py
dsa_helpers/dash/header_callbacks.py
dsa_helpers/ml/__init__.py
dsa_helpers/ml/callbacks.py
dsa_helpers/ml/evaluate.py
dsa_helpers/ml/inference_results.py
dsa_helpers/ml/metrics.py
dsa_helpers/ml/datasets/SegFormerSegmentationDataset.py
dsa_helpers/ml/datasets/__init__.py
dsa_helpers/ml/datasets/utils.py
dsa_helpers/ml/object_detection/__init__.py
dsa_helpers/ml/object_detection/get_pearce_roi_images.py
dsa_helpers/ml/object_detection/tile_image.py
dsa_helpers/ml/object_detection/utils.py
dsa_helpers/ml/segformer_semantic_segmentation/__init__.py
dsa_helpers/ml/segformer_semantic_segmentation/datasets.py
dsa_helpers/ml/segformer_semantic_segmentation/evaluate.py
dsa_helpers/ml/segformer_semantic_segmentation/inference.py
dsa_helpers/ml/segformer_semantic_segmentation/train.py
dsa_helpers/ml/segformer_semantic_segmentation/transforms.py
dsa_helpers/ml/segformer_semantic_segmentation/utils.py
dsa_helpers/ml/transforms/__init__.py
dsa_helpers/ml/transforms/segformer_transforms.py
dsa_helpers/ml/yolo/__init__.py
dsa_helpers/ml/yolo/inference.py
dsa_helpers/ml/yolo/tiling.py
dsa_helpers/ml/yolo/train.py
dsa_helpers-3.1.7.dist-info/licenses/LICENSE
dsa_helpers-3.1.7.dist-info/METADATA
dsa_helpers-3.1.7.dist-info/WHEEL
dsa_helpers-3.1.7.dist-info/top_level.txt
dsa_helpers-3.1.7.dist-info/RECORD
