Metadata-Version: 2.4
Name: dsa_helpers
Version: 3.1.7
Summary: Utility functions for working with the DSA girder client.
Author-email: "Juan C. Vizcarra" <jvizcar@emory.edu>
Maintainer-email: "Juan C. Vizcarra" <jvizcar@emory.edu>
Project-URL: Repository, https://github.com/Gutman-Lab/dsa-python-utils
Keywords: dsa,girder,girder_client
Classifier: Programming Language :: Python :: 3
Classifier: License :: OSI Approved :: MIT License
Requires-Python: >=3.8
License-File: LICENSE
Requires-Dist: matplotlib
Requires-Dist: girder-client
Requires-Dist: numpy
Requires-Dist: setuptools
Requires-Dist: pandas
Requires-Dist: pymongo
Requires-Dist: pillow
Requires-Dist: dash
Requires-Dist: dash-bootstrap-components
Requires-Dist: shapely
Requires-Dist: geopandas
Requires-Dist: rasterio
Requires-Dist: colorama
Requires-Dist: rdp
Requires-Dist: histomicstk
Requires-Dist: pykdtree
Provides-Extra: opencv
Requires-Dist: opencv-python; extra == "opencv"
Provides-Extra: opencv-headless
Requires-Dist: opencv-python-headless; extra == "opencv-headless"
Provides-Extra: ultrayltics
Requires-Dist: ultrayltics; extra == "ultrayltics"
Provides-Extra: segformer
Requires-Dist: transformers[torch]; extra == "segformer"
Requires-Dist: datasets; extra == "segformer"
Requires-Dist: torchvision; extra == "segformer"
Requires-Dist: albumentations; extra == "segformer"
Provides-Extra: all
Requires-Dist: opencv-python-headless; extra == "all"
Requires-Dist: ultrayltics; extra == "all"
Requires-Dist: transformers[torch]; extra == "all"
Requires-Dist: datasets; extra == "all"
Requires-Dist: torchvision; extra == "all"
Requires-Dist: albumentations; extra == "all"
Dynamic: license-file
